sts_auth/__init__.py
sts_auth/_version.py
sts_auth/cli.py
sts_auth/config.py
sts_auth/okta.py
sts_auth/profile.py
sts_auth/profile_set.py
sts_auth/stsauth.py
sts_auth/utils.py
stsauth-2.0.1.dist-info/licenses/LICENSE
tests/__init__.py
tests/test_config.py
tests/test_profile.py
tests/test_stsauth.py
tests/test_utils.py
tests/fixtures/__init__.py
tests/fixtures/fixtures.py
tests/fixtures/html/account_list.html
tests/fixtures/html/saml_account.html
tests/fixtures/html/saml_role.html
stsauth-2.0.1.dist-info/METADATA
stsauth-2.0.1.dist-info/WHEEL
stsauth-2.0.1.dist-info/entry_points.txt
stsauth-2.0.1.dist-info/top_level.txt
stsauth-2.0.1.dist-info/RECORD
