Metadata-Version: 2.4
Name: stsauth
Version: 2.0.1
Summary: CLI tool for fetching AWS tokens.
Author-email: Scott Hamrick <scott@scotthamrick.com>
License: MIT License
Project-URL: Homepage, https://github.com/cshamrick/stsauth
Project-URL: Repository, https://github.com/cshamrick/stsauth
Project-URL: Issues, https://github.com/cshamrick/stsauth/issues
Project-URL: Changelog, https://github.com/cshamrick/stsauth/blob/main/CHANGELOG.md
Classifier: Development Status :: 4 - Beta
Classifier: Intended Audience :: Developers
Classifier: Programming Language :: Python :: 3
Classifier: Programming Language :: Python :: 3.8
Classifier: Programming Language :: Python :: 3.9
Classifier: Operating System :: OS Independent
Classifier: Topic :: Utilities
Requires-Python: >=3.8
License-File: LICENSE
Requires-Dist: boto3<2
Requires-Dist: beautifulsoup4<5
Requires-Dist: Click<9,>=8
Requires-Dist: click-log<0.4
Requires-Dist: requests<3
Requires-Dist: requests_ntlm<2
Requires-Dist: lxml<5
Requires-Dist: pyotp<3
Requires-Dist: urllib3<1.30
Requires-Dist: importlib_metadata; python_version < "3.8"
Requires-Dist: backoff<2.3
Dynamic: license-file
